azurebatchload/__init__.py
azurebatchload/checks.py
azurebatchload/core.py
azurebatchload/download.py
azurebatchload/upload.py
azurebatchload/utils.py
azurebatchload-0.6.3.dist-info/LICENSE
azurebatchload-0.6.3.dist-info/METADATA
azurebatchload-0.6.3.dist-info/WHEEL
azurebatchload-0.6.3.dist-info/top_level.txt
azurebatchload-0.6.3.dist-info/RECORD
