Metadata-Version: 2.1
Name: azurebatchload
Version: 0.6.3
Summary: Download and upload files in batches from Azure Blob Storage Containers
Home-page: https://github.com/zypp-io/azure-batch-load
Author: Erfan Nariman, Melvin Folkers
Author-email: hello@zypp.io
Project-URL: Bug Tracker, https://github.com/zypp-io/azure-batch-load/issues
Project-URL: Source, https://github.com/zypp-io/azure-batch-load
Keywords: python,azure,blob,download,upload,batch
Classifier: Programming Language :: Python :: 3
Classifier: License :: OSI Approved :: MIT License
Classifier: Operating System :: OS Independent
Requires-Python: >=3.7
License-File: LICENSE
Requires-Dist: azure-storage-blob (>=12.8.1)
Requires-Dist: pandas (>=1.4.1)
